gitdata/web/__init__.py
gitdata/web/test.py
gitdatalab/__version__.py
gitdatalab/context.py
gitdatalab/dev.py
gitdatalab/web/__init__.py
gitdatalab/web/wsgi.py
gitdatalab-0.0.2.dist-info/METADATA
gitdatalab-0.0.2.dist-info/WHEEL
gitdatalab-0.0.2.dist-info/top_level.txt
gitdatalab-0.0.2.dist-info/RECORD
