Metadata-Version: 2.1
Name: gitdatalab
Version: 0.0.2
Summary: Data application development environment
Home-page: https://github.com/gitdata/gitdatalab
Author: DSI Labs
Author-email: support@gitdata.com
License: UNKNOWN
Platform: UNKNOWN
Classifier: Development Status :: 1 - Planning
Classifier: Environment :: Console
Classifier: Intended Audience :: Developers
Classifier: Intended Audience :: Science/Research
Classifier: License :: OSI Approved :: MIT License
Classifier: Operating System :: OS Independent
Classifier: Programming Language :: Python
Classifier: Programming Language :: Python :: 3
Classifier: Programming Language :: Python :: 3.6
Classifier: Programming Language :: Python :: 3.7
Classifier: Programming Language :: Python :: 3.8
Classifier: Programming Language :: Python :: 3 :: Only
Classifier: Topic :: Database :: Front-Ends
Requires-Dist: gitdata-lib (>=0.0.10)
Requires-Dist: livereload (>=2.5.1)
Requires-Dist: flask
